petrichor/__init__.py
petrichor/core/__init__.py
petrichor/core/singleton_meta.py
petrichor/core/exceptions/__init__.py
petrichor/core/exceptions/http_exceptions.py
petrichor/data/__init__.py
petrichor/data/base_query.py
petrichor/domain/__init__.py
petrichor/domain/base_schemas.py
petrichor/domain/base_service.py
petrichor-0.0.1.dist-info/METADATA
petrichor-0.0.1.dist-info/WHEEL
petrichor-0.0.1.dist-info/top_level.txt
petrichor-0.0.1.dist-info/RECORD
