Metadata-Version: 2.1
Name: petrichor
Version: 0.0.1
Summary: Domain Helper
Home-page: https://github.com/nymann/petrichor
Maintainer: Kristian Nymann Jakobsen
Maintainer-email: kristian@nymann.dev
License: UNKNOWN
Platform: UNKNOWN
Requires-Python: >=3.9
Requires-Dist: fastapi
Requires-Dist: pydantic
Requires-Dist: asyncpg
Provides-Extra: dev
Requires-Dist: isort ; extra == 'dev'
Requires-Dist: wemake-python-styleguide ; extra == 'dev'
Requires-Dist: mypy ; extra == 'dev'
Requires-Dist: black ; extra == 'dev'
Requires-Dist: dlint ; extra == 'dev'
Requires-Dist: nitpick ; extra == 'dev'
Requires-Dist: cohesion ; extra == 'dev'
Requires-Dist: flake8 ; extra == 'dev'
Requires-Dist: pyformat ; extra == 'dev'
Requires-Dist: add-trailing-comma ; extra == 'dev'
Requires-Dist: pre-commit ; extra == 'dev'
Requires-Dist: devtools[pygments] ; extra == 'dev'
